plexapi/__init__.py
plexapi/alert.py
plexapi/audio.py
plexapi/base.py
plexapi/client.py
plexapi/collection.py
plexapi/config.py
plexapi/const.py
plexapi/exceptions.py
plexapi/gdm.py
plexapi/library.py
plexapi/media.py
plexapi/mixins.py
plexapi/myplex.py
plexapi/photo.py
plexapi/playlist.py
plexapi/playqueue.py
plexapi/server.py
plexapi/settings.py
plexapi/sonos.py
plexapi/sync.py
plexapi/utils.py
plexapi/video.py
PlexAPI-4.15.16.dist-info/AUTHORS.txt
PlexAPI-4.15.16.dist-info/LICENSE.txt
PlexAPI-4.15.16.dist-info/METADATA
PlexAPI-4.15.16.dist-info/WHEEL
PlexAPI-4.15.16.dist-info/top_level.txt
PlexAPI-4.15.16.dist-info/RECORD
