Metadata-Version: 2.1
Name: PlexAPI
Version: 4.15.16
Summary: Python bindings for the Plex API.
Home-page: https://github.com/pkkid/python-plexapi
Author: Michael Shepanski
Author-email: michael.shepanski@gmail.com
License: UNKNOWN
Keywords: plex,api
Platform: UNKNOWN
Classifier: Operating System :: OS Independent
Classifier: Programming Language :: Python :: 3
Classifier: License :: OSI Approved :: BSD License
Requires-Python: >=3.8
Provides-Extra: alert
